Python 3.6.9

  6           0 LOAD_CONST               1 (67)
              2 LOAD_CONST               2 (68)
              4 LOAD_CONST               2 (68)
              6 LOAD_CONST               1 (67)
              8 LOAD_CONST               3 (50)
             10 LOAD_CONST               3 (50)
             12 LOAD_CONST               4 (123)
             14 LOAD_CONST               5 (87)
             16 LOAD_CONST               6 (101)
             18 LOAD_CONST               7 (108)
             20 LOAD_CONST               8 (99)
             22 LOAD_CONST               9 (111)
             24 LOAD_CONST              10 (109)
             26 LOAD_CONST               6 (101)
             28 LOAD_CONST              11 (95)
             30 LOAD_CONST              12 (116)
             32 LOAD_CONST               9 (111)
             34 LOAD_CONST              11 (95)
             36 LOAD_CONST              13 (83)
             38 LOAD_CONST              14 (105)
             40 LOAD_CONST              15 (110)
             42 LOAD_CONST              16 (103)
             44 LOAD_CONST              17 (97)
             46 LOAD_CONST              18 (112)
             48 LOAD_CONST               9 (111)
             50 LOAD_CONST              19 (114)
             52 LOAD_CONST               6 (101)
             54 LOAD_CONST              11 (95)
             56 LOAD_CONST               3 (50)
             58 LOAD_CONST              20 (48)
             60 LOAD_CONST               3 (50)
             62 LOAD_CONST               3 (50)
             64 LOAD_CONST              11 (95)
             66 LOAD_CONST               2 (68)
             68 LOAD_CONST              13 (83)
             70 LOAD_CONST              21 (84)
             72 LOAD_CONST              22 (65)
             74 LOAD_CONST              11 (95)
             76 LOAD_CONST               1 (67)
             78 LOAD_CONST              21 (84)
             80 LOAD_CONST              23 (70)
             82 LOAD_CONST              24 (125)
             84 BUILD_LIST              42
             86 STORE_FAST               0 (key)

  7          88 LOAD_CONST              25 (19)
             90 LOAD_CONST              26 (21)
             92 LOAD_CONST              26 (21)
             94 LOAD_CONST              25 (19)
             96 LOAD_CONST              27 (0)
             98 LOAD_CONST              27 (0)
            100 LOAD_CONST              27 (0)
            102 LOAD_CONST              20 (48)
            104 LOAD_CONST              20 (48)
            106 LOAD_CONST              28 (93)
            108 LOAD_CONST              29 (86)
            110 LOAD_CONST              20 (48)
            112 LOAD_CONST              30 (46)
            114 LOAD_CONST              31 (9)
            116 LOAD_CONST              32 (15)
            118 LOAD_CONST              33 (43)
            120 LOAD_CONST              34 (31)
            122 LOAD_CONST              35 (10)
            124 LOAD_CONST              16 (103)
            126 LOAD_CONST              20 (48)
            128 LOAD_CONST              36 (23)
            130 LOAD_CONST              26 (21)
            132 LOAD_CONST              27 (0)
            134 LOAD_CONST              37 (73)
            136 LOAD_CONST              38 (61)
            138 LOAD_CONST              39 (45)
            140 LOAD_CONST              21 (84)
            142 LOAD_CONST              40 (106)
            144 LOAD_CONST              10 (109)
            146 LOAD_CONST              41 (98)
            148 LOAD_CONST              42 (6)
            150 LOAD_CONST              43 (7)
            152 LOAD_CONST              44 (51)
            154 LOAD_CONST              45 (27)
            156 LOAD_CONST              46 (22)
            158 LOAD_CONST               6 (101)
            160 LOAD_CONST              47 (120)
            162 LOAD_CONST              35 (10)
            164 LOAD_CONST              48 (4)
            166 LOAD_CONST              49 (107)
            168 LOAD_CONST              50 (121)
            170 LOAD_CONST              27 (0)
            172 BUILD_LIST              42
            174 STORE_FAST               1 (result)
            176 LOAD_CONST               0 (None)
            178 RETURN_VALUE
 12           0 SETUP_LOOP              46 (to 48)
              2 LOAD_GLOBAL              0 (range)
              4 LOAD_CONST               1 (0)
              6 LOAD_GLOBAL              1 (len)
              8 LOAD_GLOBAL              2 (key)
             10 CALL_FUNCTION            1
             12 CALL_FUNCTION            2
             14 GET_ITER
        >>   16 FOR_ITER                28 (to 46)
             18 STORE_FAST               0 (i)

 13          20 LOAD_FAST                1 (decrypted)
             22 LOAD_GLOBAL              3 (chr)
             24 LOAD_GLOBAL              4 (result)
             26 LOAD_FAST                0 (i)
             28 BINARY_SUBSCR
             30 LOAD_GLOBAL              2 (key)
             32 LOAD_FAST                0 (i)
             34 BINARY_SUBSCR
             36 BINARY_XOR
             38 CALL_FUNCTION            1
             40 INPLACE_ADD
             42 STORE_FAST               1 (decrypted)
             44 JUMP_ABSOLUTE           16
        >>   46 POP_BLOCK
        >>   48 LOAD_CONST               0 (None)
             50 RETURN_VALUE
 16           0 SETUP_LOOP             152 (to 154)
              2 LOAD_GLOBAL              0 (decrypted)
              4 GET_ITER
        >>    6 FOR_ITER               144 (to 152)
              8 STORE_FAST               0 (i)

 17          10 LOAD_CONST               1 ('a')
             12 LOAD_FAST                0 (i)
             14 DUP_TOP
             16 ROT_THREE
             18 COMPARE_OP               1 (<=)
             20 JUMP_IF_FALSE_OR_POP    28
             22 LOAD_CONST               2 ('z')
             24 COMPARE_OP               1 (<=)
             26 JUMP_FORWARD             4 (to 32)
        >>   28 ROT_TWO
             30 POP_TOP
        >>   32 POP_JUMP_IF_FALSE       76

 18          34 LOAD_FAST                1 (original)
             36 LOAD_GLOBAL              1 (chr)
             38 LOAD_FAST                0 (i)
             40 LOAD_CONST               3 ('m')
             42 COMPARE_OP               1 (<=)
             44 POP_JUMP_IF_FALSE       58
             46 LOAD_GLOBAL              2 (ord)
             48 LOAD_FAST                0 (i)
             50 CALL_FUNCTION            1
             52 LOAD_CONST               4 (13)
             54 BINARY_ADD
             56 JUMP_FORWARD            10 (to 68)
        >>   58 LOAD_GLOBAL              2 (ord)
             60 LOAD_FAST                0 (i)
             62 CALL_FUNCTION            1
             64 LOAD_CONST               4 (13)
             66 BINARY_SUBTRACT
        >>   68 CALL_FUNCTION            1
             70 INPLACE_ADD
             72 STORE_FAST               1 (original)
             74 JUMP_ABSOLUTE            6

 19     >>   76 LOAD_CONST               5 ('A')
             78 LOAD_FAST                0 (i)
             80 DUP_TOP
             82 ROT_THREE
             84 COMPARE_OP               1 (<=)
             86 JUMP_IF_FALSE_OR_POP    94
             88 LOAD_CONST               6 ('Z')
             90 COMPARE_OP               1 (<=)
             92 JUMP_FORWARD             4 (to 98)
        >>   94 ROT_TWO
             96 POP_TOP
        >>   98 POP_JUMP_IF_FALSE      142

 20         100 LOAD_FAST                1 (original)
            102 LOAD_GLOBAL              1 (chr)
            104 LOAD_FAST                0 (i)
            106 LOAD_CONST               7 ('M')
            108 COMPARE_OP               1 (<=)
            110 POP_JUMP_IF_FALSE      124
            112 LOAD_GLOBAL              2 (ord)
            114 LOAD_FAST                0 (i)
            116 CALL_FUNCTION            1
            118 LOAD_CONST               4 (13)
            120 BINARY_ADD
            122 JUMP_FORWARD            10 (to 134)
        >>  124 LOAD_GLOBAL              2 (ord)
            126 LOAD_FAST                0 (i)
            128 CALL_FUNCTION            1
            130 LOAD_CONST               4 (13)
            132 BINARY_SUBTRACT
        >>  134 CALL_FUNCTION            1
            136 INPLACE_ADD
            138 STORE_FAST               1 (original)
            140 JUMP_ABSOLUTE            6

 22     >>  142 LOAD_FAST                1 (original)
            144 LOAD_FAST                0 (i)
            146 INPLACE_ADD
            148 STORE_FAST               1 (original)
            150 JUMP_ABSOLUTE            6
        >>  152 POP_BLOCK
        >>  154 LOAD_CONST               0 (None)
            156 RETURN_VALUE
